{
  "slug": "humans-matter",
  "name": "Humans Matter",
  "url": "https://www.thematchainitiative.com/supplier/humans-matter",
  "description": "Humans Matter is a forward-thinking agency committed to creating positive change through innovative and evidence-based approaches. We help organizations design and implement  sustainable transformations in different arenas: mission and strategy, culture and people, skills and talent management, and innovation leveraging a solid expertise in both business matters and cognitive science. Powered by 140+ employees with a wide range of expertise (neuroscientists, researchers, designers, consultants, pedagogic engineers, developers, etc.), we accompany your mindset, culture and behavioral transformation in the domains of @work, @health, @learn and @society. Humans Matter is a forward-thinking agency committed to creating positive change through innovative and evidence-based approaches. We help organizations design and implement  sustainable transformations in different arenas: mission and strategy, culture and people, skills and talent management, and innovation leveraging a solid expertise in both business matters and cognitive science.",
  "website": "https://cdn.prod.website-files.com/5e940b86961046721a7e92b5/656dcf75a0a4556c731048bd_GreenOffice_AllSolutionsataGlance.pdf",
  "email": "m.veillon@humansmatter.co",
  "phone": "",
  "services": [
    "Consulting",
    "Waste Management",
    "Carbon Offset",
    "Sustainability"
  ],
  "certifications": [],
  "categories": []
}